corpus_content/__init__.py
corpus_content/author.py
corpus_content/block.py
corpus_content/decision.py
corpus_content/opinion.py
corpus_content/watch.py
corpus_content/utils/__init__.py
corpus_content/utils/annex.py
corpus_content/utils/casename.py
corpus_content/utils/courts.py
corpus_content/utils/dumper.py
corpus_content/utils/fallo.py
corpus_content/utils/formatter.py
corpus_content/utils/md.py
corpus_content/utils/phrase.py
corpus_content/utils/regex.py
corpus_content-0.1.1.dist-info/METADATA
corpus_content-0.1.1.dist-info/WHEEL
corpus_content-0.1.1.dist-info/top_level.txt
corpus_content-0.1.1.dist-info/RECORD
