Metadata-Version: 2.1
Name: corpus-content
Version: 0.1.1
Summary: Using opinion text from frontmatter-formatted markdown files, chunk into segments and itemize Philippine statutes, citations within the text.
Requires-Python: >=3.11
Requires-Dist: statute-utils >=0.6.8
Requires-Dist: citation-utils >=0.4.10
Requires-Dist: python-frontmatter >=1.1.0
Provides-Extra: dev
Requires-Dist: ipykernel >=6.29 ; extra == 'dev'
Requires-Dist: pytest >=8.0 ; extra == 'dev'
Requires-Dist: pytest-cov >=4.1 ; extra == 'dev'
Requires-Dist: sqlite-utils >=3.36 ; extra == 'dev'
Requires-Dist: watchdog >=3.0 ; extra == 'dev'
Requires-Dist: rich >=13.7 ; extra == 'dev'
Requires-Dist: build >=1.0.3 ; extra == 'dev'
Requires-Dist: twine >=4.0.2 ; extra == 'dev'
